panpan/__init__.py
panpan/greet.py
picture_replace-0.0.1.dist-info/METADATA
picture_replace-0.0.1.dist-info/WHEEL
picture_replace-0.0.1.dist-info/top_level.txt
picture_replace-0.0.1.dist-info/RECORD
