Metadata-Version: 2.1
Name: picture-replace
Version: 0.0.1
Summary: focus! 
Home-page: UNKNOWN
Author: panxianxian
License: UNKNOWN
Platform: UNKNOWN
Requires-Python: >=3
